Metadata-Version: 1.2
Name: XStatic-Asap
Version: 0.1.0
Summary: Asap 0.1 (XStatic packaging standard)
Home-page: https://www.fontsquirrel.com/fonts/asap
Maintainer: Elias Showk
Maintainer-email: eshowk@entrouvert.com
License: (same as Asap)
Keywords: asap xstatic
Platform: any
